Metadata-Version: 1.1
Name: skylinesms
Version: 1.1
Summary: A module to send sms using the Skyline SMS REST apis, www.skylinesms.com
Home-page: https://github.com/assekalala/python-skyline-sms.git
Author: Abdu Ssekalala
Author-email: assekalala@gmail.com
License: UNKNOWN
Keywords: sms,skyline
Platform: UNKNOWN
Classifier: Programming Language :: Python
Classifier: Programming Language :: Python :: 3
Classifier: Intended Audience :: Developers
Classifier: License :: OSI Approved :: Apache Software License
Classifier: Operating System :: OS Independent
Classifier: Topic :: Software Development :: Libraries :: Python Modules
Classifier: Topic :: Communications
Classifier: Development Status :: 4 - Beta
